reconciler_for_ynab/__init__.py
reconciler_for_ynab/__main__.py
reconciler_for_ynab/_main.py
reconciler_for_ynab/py.typed
reconciler_for_ynab-0.0.3.dist-info/licenses/LICENSE
testing/__init__.py
testing/fixtures.py
tests/__init__.py
tests/_main_test.py
reconciler_for_ynab-0.0.3.dist-info/METADATA
reconciler_for_ynab-0.0.3.dist-info/WHEEL
reconciler_for_ynab-0.0.3.dist-info/entry_points.txt
reconciler_for_ynab-0.0.3.dist-info/top_level.txt
reconciler_for_ynab-0.0.3.dist-info/RECORD
