Metadata-Version: 2.4
Name: reconciler_for_ynab
Version: 0.0.3
Summary: Reconciler for YNAB - Reconcile YNAB transactions to reach a target balance
Home-page: https://github.com/mxr/reconciler-for-ynab
Author: Max R
Author-email: mxr@users.noreply.github.com
License: MIT
Keywords: ynab,budget,reconcile,cli
Classifier: Programming Language :: Python :: 3
Classifier: Programming Language :: Python :: 3 :: Only
Classifier: Programming Language :: Python :: Implementation :: CPython
Classifier: Programming Language :: Python :: Implementation :: PyPy
Requires-Python: >=3.12
License-File: LICENSE
Requires-Dist: aiohttp>=3
Requires-Dist: babel
Requires-Dist: sqlite-export-for-ynab>=1.4.2
Requires-Dist: tldm>=1.0.2
Dynamic: license-file
